tests
turkle
